scru128/__init__.py
scru128/cli/__init__.py
scru128-3.0.4.dist-info/LICENSE
scru128-3.0.4.dist-info/METADATA
scru128-3.0.4.dist-info/WHEEL
scru128-3.0.4.dist-info/entry_points.txt
scru128-3.0.4.dist-info/RECORD
