Metadata-Version: 2.3
Name: scru128
Version: 3.0.4
Summary: SCRU128: Sortable, Clock and Random number-based Unique identifier
License: Apache-2.0
Keywords: identifier,uuid,guid,ulid,ksuid
Author: LiosK
Author-email: contact@mail.liosk.net
Requires-Python: >=3.9
Classifier: License :: OSI Approved :: Apache Software License
Classifier: Operating System :: OS Independent
Classifier: Programming Language :: Python :: 3
Classifier: Programming Language :: Python :: 3.9
Classifier: Programming Language :: Python :: 3.10
Classifier: Programming Language :: Python :: 3.11
Classifier: Programming Language :: Python :: 3.12
Classifier: Programming Language :: Python :: 3.13
Project-URL: Homepage, https://github.com/scru128/python
